frightcrawler/__init__.py
frightcrawler/frightcrawler.py
frightcrawler-0.0.8.dist-info/LICENSE
frightcrawler-0.0.8.dist-info/METADATA
frightcrawler-0.0.8.dist-info/WHEEL
frightcrawler-0.0.8.dist-info/entry_points.txt
frightcrawler-0.0.8.dist-info/top_level.txt
frightcrawler-0.0.8.dist-info/RECORD
