Metadata-Version: 2.1
Name: frightcrawler
Version: 0.0.8
Summary: MtG deck legality checker
Home-page: https://github.com/charlesrocket/frightcrawler
Author: charlesrocket
License: MIT
Platform: UNKNOWN
Classifier: License :: OSI Approved :: MIT License
Classifier: Operating System :: OS Independent
Classifier: Programming Language :: Python :: 3
Classifier: Natural Language :: English
Requires-Python: >=3.6
Requires-Dist: dictor (>=0.1.6)
Requires-Dist: requests-cache (>=0.6.0)
